proqub/__init__.py
proqub/processor.py
proqub-1.0.3.dist-info/licenses/LICENSE
proqub-1.0.3.dist-info/METADATA
proqub-1.0.3.dist-info/WHEEL
proqub-1.0.3.dist-info/top_level.txt
proqub-1.0.3.dist-info/RECORD
