Metadata-Version: 2.4
Name: proqub
Version: 1.0.3
Summary: A Python library for processing hyperspectral data cubes.
Home-page: https://github.com/pras2005/proqub
Author: Prasad, Aryan, Tanishka
Author-email: prasaddesale05@gmail.com,burhadearyan@gmail.com
License: MIT License
Classifier: Programming Language :: Python :: 3
Classifier: License :: OSI Approved :: MIT License
Classifier: Operating System :: OS Independent
Classifier: Intended Audience :: Science/Research
Classifier: Topic :: Scientific/Engineering :: GIS
Requires-Python: >=3.7
License-File: LICENSE
Requires-Dist: numpy
Requires-Dist: pandas
Requires-Dist: spectral
Requires-Dist: matplotlib
Requires-Dist: plotly
Dynamic: license-file
